djamago/__init__.py
djamago/contrib/__init__.py
djamago/contrib/spellcheck/__init__.py
djamago/contrib/spellcheck/correction.py
djamago-0.0.1.dist-info/LICENSE
djamago-0.0.1.dist-info/METADATA
djamago-0.0.1.dist-info/WHEEL
djamago-0.0.1.dist-info/top_level.txt
djamago-0.0.1.dist-info/RECORD
